nwb_mcp_server/__init__.py
nwb_mcp_server/py.typed
nwb_mcp_server/server.py
nwb_mcp_server-0.1.3.dist-info/licenses/LICENSE
nwb_mcp_server-0.1.3.dist-info/METADATA
nwb_mcp_server-0.1.3.dist-info/WHEEL
nwb_mcp_server-0.1.3.dist-info/entry_points.txt
nwb_mcp_server-0.1.3.dist-info/top_level.txt
nwb_mcp_server-0.1.3.dist-info/RECORD
