Metadata-Version: 2.4
Name: nwb-mcp-server
Version: 0.1.3
Summary: An MCP server for accessing NWB (Neurodata Without Borders) files, providing AI agents with easy access to neuroscience data.
Author-email: bjhardcastle <ben.hardcastle@alleninstitute.org>
Requires-Python: >=3.10
License-File: LICENSE
Requires-Dist: fastmcp>=2.10.4
Requires-Dist: lazynwb>=0.2.71
Dynamic: license-file
